snippe/__init__.py
snippe/client.py
snippe/exceptions.py
snippe/models.py
snippe/py.typed
snippe/types.py
snippe/webhooks.py
snippe-0.1.1.dist-info/METADATA
snippe-0.1.1.dist-info/WHEEL
snippe-0.1.1.dist-info/RECORD
