Metadata-Version: 2.4
Name: snippe
Version: 0.1.1
Summary: Official Python SDK for Snippe Payment API
Project-URL: Homepage, https://snippe.sh
Project-URL: Documentation, https://documenter.getpostman.com/view/36488510/2sBXViiWAV#6beb6d54-34a1-4c9c-8a19-acd92a865711
Project-URL: Repository, https://github.com/Neurotech-HQ/snippe-python-sdk
Author-email: Nassdaq <mwaijegakelvin@gmail.com>
License-Expression: MIT
Keywords: Tanzania Payment,africa,fintech,mobile-money,snippe
Classifier: Development Status :: 4 - Beta
Classifier: Intended Audience :: Developers
Classifier: License :: OSI Approved :: MIT License
Classifier: Programming Language :: Python :: 3
Classifier: Programming Language :: Python :: 3.8
Classifier: Programming Language :: Python :: 3.9
Classifier: Programming Language :: Python :: 3.10
Classifier: Programming Language :: Python :: 3.11
Classifier: Programming Language :: Python :: 3.12
Classifier: Topic :: Software Development :: Libraries :: Python Modules
Requires-Python: >=3.10
Requires-Dist: httpx>=0.24.0
Provides-Extra: dev
Requires-Dist: pytest-asyncio>=0.21.0; extra == 'dev'
Requires-Dist: pytest>=7.0.0; extra == 'dev'
Requires-Dist: respx>=0.20.0; extra == 'dev'
